MANIFEST.in
README.rst
setup.py
custom_anonymous/__init__.py
custom_anonymous/middleware.py
django_custom_anonymous.egg-info/PKG-INFO
django_custom_anonymous.egg-info/SOURCES.txt
django_custom_anonymous.egg-info/dependency_links.txt
django_custom_anonymous.egg-info/top_level.txt